aicalm_contrib/README.md
aicalm_contrib/agents/__init__.py
aicalm_contrib/agents/time_series_analyzer/__init__.py
k1st_contrib/__init__.py
k1st_contrib/img_classif/ImageNet-Classes.json
k1st_contrib/img_classif/README.md
k1st_contrib/img_classif/__init__.py
k1st_contrib/img_classif/imagenet.py
k1st_contrib/img_classif/util.py
k1st_contrib/iot_mgmt/README.md
k1st_contrib/iot_mgmt/api.py
k1st_contrib/iot_mgmt/data/admin.py
k1st_contrib/iot_mgmt/data/apps.py
k1st_contrib/iot_mgmt/data/filters.py
k1st_contrib/iot_mgmt/data/migrations/0001_initial.py
k1st_contrib/iot_mgmt/data/migrations/0002_equipmentuniquetype_data_fields.py
k1st_contrib/iot_mgmt/data/migrations/0003_equipmentinstance.py
k1st_contrib/iot_mgmt/data/migrations/0004_auto_20180103_1007.py
k1st_contrib/iot_mgmt/data/migrations/0005_auto_20180103_1059.py
k1st_contrib/iot_mgmt/data/migrations/0006_auto_20180410_1904.py
k1st_contrib/iot_mgmt/data/migrations/0007_auto_20180703_1156.py
k1st_contrib/iot_mgmt/data/migrations/0008_equipmentinstanceassociation.py
k1st_contrib/iot_mgmt/data/migrations/0009_auto_20180724_2039.py
k1st_contrib/iot_mgmt/data/migrations/0010_auto_20180803_0015.py
k1st_contrib/iot_mgmt/data/migrations/0011_auto_20180803_0024.py
k1st_contrib/iot_mgmt/data/migrations/0012_auto_20180803_0033.py
k1st_contrib/iot_mgmt/data/migrations/0013_auto_20180803_1030.py
k1st_contrib/iot_mgmt/data/migrations/0014_auto_20180803_1031.py
k1st_contrib/iot_mgmt/data/migrations/0015_equipmentuniquetypegroup_equipment_data_fields.py
k1st_contrib/iot_mgmt/data/migrations/0016_auto_20180908_1532.py
k1st_contrib/iot_mgmt/data/migrations/0017_auto_20180909_0502.py
k1st_contrib/iot_mgmt/data/migrations/0018_auto_20180926_1510.py
k1st_contrib/iot_mgmt/data/migrations/0019_auto_20181002_1415.py
k1st_contrib/iot_mgmt/data/migrations/0020_remove_equipmentdatafield_nullable.py
k1st_contrib/iot_mgmt/data/migrations/0021_auto_20181025_0733.py
aicalm_contrib-23.6.15.0.dist-info/LICENSE
aicalm_contrib-23.6.15.0.dist-info/METADATA
aicalm_contrib-23.6.15.0.dist-info/WHEEL
aicalm_contrib-23.6.15.0.dist-info/RECORD
